{
  "animateLoading": true,
  "borderRadius": "{{appsmith.theme.borderRadius.appBorderRadius}}",
  "bottomRow": 28,
  "displayName": "Text",
  "dynamicBindingPathList": [
    {
      "key": "truncateButtonColor"
    },
    {
      "key": "fontFamily"
    },
    {
      "key": "borderRadius"
    }
  ],
  "dynamicHeight": "AUTO_HEIGHT",
  "dynamicTriggerPathList": [],
  "fontFamily": "{{appsmith.theme.fontFamily.appFont}}",
  "fontSize": "1.25rem",
  "fontStyle": "BOLD",
  "hideCard": false,
  "iconSVG": "https://appcdn.appsmith.com/static/media/icon.a47d6d5dbbb718c4dc4b2eb4f218c1b7.svg",
  "isDeprecated": false,
  "isLoading": false,
  "isVisible": true,
  "key": "igo4evb5e5",
  "leftColumn": 0,
  "maxDynamicHeight": 9000,
  "minDynamicHeight": 4,
  "minWidth": 450,
  "mobileBottomRow": 9,
  "mobileLeftColumn": 1,
  "mobileRightColumn": 17,
  "mobileTopRow": 5,
  "originalBottomRow": 28,
  "originalTopRow": 24,
  "overflow": "NONE",
  "parentColumnSpace": 13.9375,
  "parentId": "ba8tafscah",
  "parentRowSpace": 10,
  "renderMode": "CANVAS",
  "responsiveBehavior": "fill",
  "rightColumn": 16,
  "searchTags": [
    "typography",
    "paragraph",
    "label"
  ],
  "shouldTruncate": false,
  "tags": [
    "Suggested",
    "Content"
  ],
  "text": "Delivery Location",
  "textAlign": "LEFT",
  "textColor": "#231F20",
  "topRow": 24,
  "truncateButtonColor": "{{appsmith.theme.colors.primaryColor}}",
  "type": "TEXT_WIDGET",
  "version": 1,
  "widgetId": "aky68wfr3r",
  "widgetName": "txt_deliveryLocation"
}